{
  "titulo": "Facultad de Geografía e Historia",
  "ubicacion": "Campus del Obelisco",
  "descripcion": "La Facultad de Geografía e Historia de la ULPGC tiene su sede actual en el edificio Agustín Millares Carló, Campus del Obelisco, en Las Palmas de Gran Canaria y es el órgano docente y de gestión administrativa responsable de definir, organizar, coordinar y gestionar las enseñanzas de Grado y Posgrado en Historia, Geografía y Patrimonio. La Facultad está comprometida con la mejora continua de la calidad y la eficiencia de la enseñanza, apostando por una visión innovadora en la docencia, la investigación, la gestión y las actividades de impacto social.",
  "enlace": "http://fgh.ulpgc.es/",
  "enlace_imagen": "https://joseangulo.github.io/StreamingAssets/Buildings/Obelisco/images/edificio_humanidades.jpg"
}